performance_tester/__init__.py
performance_tester/_version.py
performance_tester/time.py
performance_tester-1.1.3.dist-info/METADATA
performance_tester-1.1.3.dist-info/WHEEL
performance_tester-1.1.3.dist-info/top_level.txt
performance_tester-1.1.3.dist-info/RECORD
