Metadata-Version: 2.1
Name: performance-tester
Version: 1.1.3
Summary: Software for testing performance
Author: junnaka51 team
License: Apache 2.0
Project-URL: homepage, https://github.com/junnaka51/performance_tester
Project-URL: repository, https://github.com/junnaka51/performance_tester
Requires-Python: >=3.7
